sentinel_local.py
sentinel_local/__init__.py
sentinel_local/main.py
src/__init__.py
src/__main__.py
src/utils.py
sentinel_local-0.1.12.1.dist-info/METADATA
sentinel_local-0.1.12.1.dist-info/WHEEL
sentinel_local-0.1.12.1.dist-info/top_level.txt
sentinel_local-0.1.12.1.dist-info/RECORD
