Metadata-Version: 2.1
Name: sentinel-local
Version: 0.1.12.1
Summary: Local Processing of Data Based on CXL Created Algorithms
Home-page: https://github.com/cxl-garage/sentinel-laptop
Author: Sam Kelly
Author-email: sam@conservationxlabs.org
License: UNKNOWN
Platform: UNKNOWN
Classifier: License :: OSI Approved :: MIT License
Classifier: Programming Language :: Python :: 3
Classifier: Programming Language :: Python :: 3.7
Requires-Dist: docker
Requires-Dist: GPUtil
Requires-Dist: numpy
Requires-Dist: pandas
Requires-Dist: Pillow
Requires-Dist: requests
Requires-Dist: tqdm
Requires-Dist: google-cloud-artifact-registry
